{
  "sections": {
    "05e09d4d-92ad-4058-a1d7-2d438520a652": {
      "type": "collection_button_slider",
      "blocks": {
        "e235dedb-3726-4c7d-a992-74c2ccd9f37b": {
          "type": "text",
          "settings": {
            "menu_text": "Golfing ShmewW",
            "link": "shopify:\/\/collections\/women",
            "checkbox": true
          }
        },
        "cc7ebb3b-05cf-4540-b2d3-0f07841ba5e7": {
          "type": "text",
          "settings": {
            "menu_text": "Women Love To ShmewW",
            "link": "shopify:\/\/collections\/women-love-to-shmeww",
            "checkbox": false
          }
        },
        "b43b743f-a09d-42cf-b967-b2cb04c4eaec": {
          "type": "text",
          "settings": {
            "menu_text": "ShmewW Accessories",
            "link": "shopify:\/\/collections\/accessories",
            "checkbox": false
          }
        },
        "c6cd5c84-d0bb-46a8-9cf5-365c6f25dc3f": {
          "type": "text",
          "settings": {
            "menu_text": "Mens ShmewW Swag",
            "link": "shopify:\/\/collections\/mens-shmeww-swag",
            "checkbox": false
          }
        },
        "3259c7f9-1f5d-4f61-b421-96f9d4bcdd5c": {
          "type": "text",
          "settings": {
            "menu_text": "I Stand With Israel",
            "link": "shopify:\/\/collections\/i-stand-with-israel",
            "checkbox": false
          }
        },
        "aa6e97ec-55a3-4d31-9dca-d18cd9096a48": {
          "type": "text",
          "settings": {
            "menu_text": "Shop All",
            "link": "shopify:\/\/collections",
            "checkbox": false
          }
        },
        "3b5ad23d-b236-4ce1-bb16-c53b126cd86b": {
          "type": "text",
          "settings": {
            "menu_text": "Unisex",
            "link": "shopify:\/\/collections\/unisex",
            "checkbox": false
          }
        }
      },
      "block_order": [
        "e235dedb-3726-4c7d-a992-74c2ccd9f37b",
        "cc7ebb3b-05cf-4540-b2d3-0f07841ba5e7",
        "b43b743f-a09d-42cf-b967-b2cb04c4eaec",
        "c6cd5c84-d0bb-46a8-9cf5-365c6f25dc3f",
        "3259c7f9-1f5d-4f61-b421-96f9d4bcdd5c",
        "aa6e97ec-55a3-4d31-9dca-d18cd9096a48",
        "3b5ad23d-b236-4ce1-bb16-c53b126cd86b"
      ],
      "settings": {
      }
    },
    "0e5b9ff2-faef-4ccc-a78c-04c8577f97e7": {
      "type": "hero_banner",
      "settings": {
        "image": "shopify:\/\/shop_images\/woman-in-the-city_925x_5bca1aa1-1625-4ea1-adc3-d709b243e190.jpg",
        "heading": "Fashion, Without Limits",
        "text_color": "#a3ff00",
        "highlight_color": "#ffffff",
        "subtext": "Discover a curated selection of clothing that marries superior craftsmanship, ultimate comfort, and unparalleled style. Your perfect fit awaits.",
        "button": "Grab New Gear",
        "button_link": "shopify:\/\/collections"
      }
    },
    "e3a122ce-a757-4467-943a-830f0eac79ba": {
      "type": "feature_collection",
      "settings": {
        "heading": "GET SHMEWWED",
        "content": "Explore our newest arrivals",
        "feature_collection": "new-arrivals",
        "products_limit": 6
      }
    },
    "e623e5d7-4c52-4909-badc-b8e634abee1e": {
      "type": "hero_banner",
      "settings": {
        "image": "shopify:\/\/shop_images\/striped-blouse-fashion_925x_9a6d27e1-d1df-45e3-bb93-b67b76511cbf.jpg",
        "heading": "Beyond <span> Comfort:<\/span> Discover <span> Clothing <\/span> That Feels Like a Dream.",
        "text_color": "#ffffff",
        "highlight_color": "#ff00ff",
        "subtext": "Check Out ShmewW Womens Collections",
        "button": "Shop Now",
        "button_link": "shopify:\/\/collections\/women-love-to-shmeww"
      }
    },
    "25c87084-0b28-4d73-a6c6-6bea48b75abb": {
      "type": "look_collection",
      "blocks": {
        "ef481780-420b-4979-8ef6-cbe1f9434013": {
          "type": "collection",
          "settings": {
            "collection": "new-arrivals",
            "text": "@twincharlo"
          }
        },
        "36056e68-2449-4611-941e-55a8e5dcb860": {
          "type": "collection",
          "settings": {
            "collection": "new",
            "text": "@twincharlo"
          }
        },
        "2b37d45a-a4f9-4535-b7df-2c2a384b6654": {
          "type": "collection",
          "settings": {
            "collection": "outerwear",
            "text": "@twincharlo"
          }
        },
        "17a1f789-cc8f-42e6-b66a-f4b53e770d9b": {
          "type": "collection",
          "settings": {
            "collection": "shirts",
            "text": "@twincharlo"
          }
        },
        "a70fecf2-cfcb-4306-b003-c870707cc680": {
          "type": "collection",
          "settings": {
            "collection": "sweatshirts",
            "text": "@twincharlo"
          }
        }
      },
      "block_order": [
        "ef481780-420b-4979-8ef6-cbe1f9434013",
        "36056e68-2449-4611-941e-55a8e5dcb860",
        "2b37d45a-a4f9-4535-b7df-2c2a384b6654",
        "17a1f789-cc8f-42e6-b66a-f4b53e770d9b",
        "a70fecf2-cfcb-4306-b003-c870707cc680"
      ],
      "settings": {
        "heading": "GET THE LOOK",
        "subtext": "<p>Hit us up on Instagram to <a href=\"#\" target=\"_blank\" title=\"#\">@SHMEWW<\/a> to flex your look & get featured!<\/p>"
      }
    },
    "406531c9-0259-4d83-9fda-8748d873d146": {
      "type": "collage",
      "settings": {
        "video_link": "https:\/\/cdn.shopify.com\/videos\/c\/o\/v\/8b8d69979aaa46879e49b086d3789030.mp4",
        "title_1": "One-Piece Dress",
        "link_1": "",
        "title_2": "Party Hats",
        "link_2": "",
        "title_3": "Picnic Hats",
        "link_3": ""
      }
    },
    "7b5fab22-0054-4bd3-bc00-95b7a47aa786": {
      "type": "coming_soon",
      "blocks": {
        "37f649d2-0e9f-4642-852e-b7f64f4f9cdb": {
          "type": "coming_col",
          "settings": {
            "collection": "mens-shmeww-swag",
            "text": "COMING THIS FALL",
            "notify_text": "Notify Me"
          }
        },
        "c9ee26be-2193-4d14-ad01-5c03e0c5839d": {
          "type": "coming_col",
          "settings": {
            "collection": "womens-utility-joggers",
            "text": "COMING THIS FALL",
            "notify_text": ""
          }
        },
        "7ec0e687-f989-4c3e-9a6a-6854dfe8017b": {
          "type": "coming_col",
          "settings": {
            "collection": "stadium-vest",
            "text": "COMING THIS FALL",
            "notify_text": ""
          }
        },
        "1a7a4f47-15a5-4292-8c73-3ea8ce5e97af": {
          "type": "product",
          "settings": {
            "product": "rossignol-pursuit-16-ti-mens-skis-axl-3-120-tpx-bindings-2015",
            "text": "Available Now"
          }
        }
      },
      "block_order": [
        "37f649d2-0e9f-4642-852e-b7f64f4f9cdb",
        "c9ee26be-2193-4d14-ad01-5c03e0c5839d",
        "7ec0e687-f989-4c3e-9a6a-6854dfe8017b",
        "1a7a4f47-15a5-4292-8c73-3ea8ce5e97af"
      ],
      "settings": {
        "heading": "COMING SOON",
        "content": "Don't miss out! Sign up for alerts on upcoming product drops.",
        "drawer_text": "<p>By submitting your email you are agreeing to our<a href=\"#\">Terms of Service<\/a>and our.<br\/>You may unsubscribe at anytime.<\/p>"
      }
    },
    "1d15a425-f7c8-4a8b-96a6-933b85893480": {
      "type": "hero_video",
      "settings": {
        "video_sec": "https:\/\/cdn.shopify.com\/videos\/c\/o\/v\/7b9f2062325346e59971ec5f32964f57.mp4",
        "title_cnt": "",
        "subtext": "We exist to inspire people to make big things happen and earn everything.",
        "button_text": "Read Our Story",
        "link": "shopify:\/\/pages\/about-us"
      }
    },
    "06b56767-6a7e-41a1-a44b-eb8f447032fc": {
      "type": "faq_box",
      "blocks": {
        "6fbaa4a4-d4e1-4395-b949-cb6f1e9d6344": {
          "type": "text",
          "settings": {
            "que": "How do I determine my size?",
            "ans": "To find your perfect fit, refer to our size guide located on each product page. We provide detailed measurements and fit recommendations to help you make the right choice."
          }
        },
        "08565c36-ad62-4f08-82dd-b39a352eda35": {
          "type": "text",
          "settings": {
            "que": "Is it safe to make online payments on your website?",
            "ans": "Yes, your online payments are completely secure. We use industry-standard encryption and security protocols to protect your personal and financial information. You can shop with confidence."
          }
        },
        "2f08866f-5645-4ae4-ae90-bad4278f2fe4": {
          "type": "text",
          "settings": {
            "que": "Are the colors of the products accurate to what is shown online?",
            "ans": "We strive to display our products as accurately as possible. However, slight variations in color may occur due to differences in monitor settings. Rest assured, we quality-check all items before shipping to maintain consistency."
          }
        },
        "92e53b61-16a1-4aaf-975b-8c190214c028": {
          "type": "text",
          "settings": {
            "que": "What shipping options are available?",
            "ans": "We offer standard and expedited shipping options. Standard shipping usually takes 3-5 business days, while expedited shipping delivers within 1-2 business days. International shipping is also available; delivery times vary based on the destination."
          }
        },
        "ff7cee8a-4405-4cd6-8ffe-c6537d996b66": {
          "type": "text",
          "settings": {
            "que": "What is the quality of your clothing items?",
            "ans": "We take pride in offering high-quality clothing made from premium materials. Our products undergo rigorous quality checks to ensure they meet our standards for durability, comfort, and style."
          }
        }
      },
      "block_order": [
        "6fbaa4a4-d4e1-4395-b949-cb6f1e9d6344",
        "08565c36-ad62-4f08-82dd-b39a352eda35",
        "2f08866f-5645-4ae4-ae90-bad4278f2fe4",
        "92e53b61-16a1-4aaf-975b-8c190214c028",
        "ff7cee8a-4405-4cd6-8ffe-c6537d996b66"
      ],
      "settings": {
        "que_heading": "Have a question ? We are here to help.",
        "subtext": "Check out the most common questions our customers asked. Still have questions ? Contact our customer             support.",
        "bottomtext": "Our customer support is available monday to friday: 8am-8:30pm.",
        "time": "Average answer time: 24h",
        "mobile_text": "Our customer support is available monday to friday: 8am-8:30pm.",
        "mobile_time": "Average answer time: 24h"
      }
    },
    "d1fa8b77-b021-4105-819b-364db70036ec": {
      "type": "icon_text",
      "blocks": {
        "5840e64f-f883-4292-8280-9bb3c797e469": {
          "type": "Icon_text",
          "settings": {
            "heading": "Designed in NYC",
            "subtext": "Products designed and developed in New York City."
          }
        },
        "54889b86-d7c4-44a0-a201-dda972105e86": {
          "type": "Icon_text",
          "settings": {
            "heading": "Designed in NYC",
            "subtext": "Products designed and developed in New York City."
          }
        },
        "4bff7bce-3a18-401c-8c08-371f1a96ae78": {
          "type": "Icon_text",
          "settings": {
            "heading": "Designed in NYC",
            "subtext": "Products designed and developed in New York City."
          }
        },
        "9a28cb27-e751-450e-a1e4-abfa56777bed": {
          "type": "Icon_text",
          "settings": {
            "heading": "Designed in NYC",
            "subtext": "Products designed and developed in New York City."
          }
        }
      },
      "block_order": [
        "5840e64f-f883-4292-8280-9bb3c797e469",
        "54889b86-d7c4-44a0-a201-dda972105e86",
        "4bff7bce-3a18-401c-8c08-371f1a96ae78",
        "9a28cb27-e751-450e-a1e4-abfa56777bed"
      ],
      "settings": {
      }
    },
    "f3113dc4-eadf-4fa4-adf7-f288d07c1076": {
      "type": "popular_tags",
      "blocks": {
        "9b8d0c9d-9355-4ff8-95f6-b77fd85e02bf": {
          "type": "text",
          "settings": {
            "popular_tag": "masala",
            "link": "https:\/\/alcoeats.com\/collections\/masala"
          }
        },
        "2a8652c7-ee84-457c-afd4-c944bd432081": {
          "type": "text",
          "settings": {
            "popular_tag": "garam masala",
            "link": "https:\/\/alcoeats.com\/products\/garam-masala"
          }
        },
        "8ebccb83-b67f-4140-84fa-22524224f9b5": {
          "type": "text",
          "settings": {
            "popular_tag": "Chicken Gravies",
            "link": "https:\/\/alcoeats.com\/collections\/chicken-gravies"
          }
        },
        "494c2096-f838-4aeb-bbc2-8db24f537a88": {
          "type": "text",
          "settings": {
            "popular_tag": "Kashmiri Chilli Powder",
            "link": "https:\/\/alcoeats.com\/products\/kashmiri-chilli-powder"
          }
        },
        "a3cff885-8b20-4cfd-9c4d-dd4318f10a1d": {
          "type": "text",
          "settings": {
            "popular_tag": "Kashmiri Chilli Powder",
            "link": ""
          }
        },
        "8848b0b7-116d-4cc4-a56f-68557316b5f4": {
          "type": "text",
          "settings": {
            "popular_tag": "Chaat Masala",
            "link": "https:\/\/alcoeats.com\/products\/chaat-masala"
          }
        },
        "ea6afd91-331d-461d-bbff-911547302bc7": {
          "type": "text",
          "settings": {
            "popular_tag": "Chicken Masala",
            "link": "https:\/\/alcoeats.com\/products\/chicken-masala"
          }
        },
        "6e544a44-a8c9-45ed-a441-7e0ed28937f1": {
          "type": "text",
          "settings": {
            "popular_tag": "Curry Masala",
            "link": "https:\/\/alcoeats.com\/products\/alco-curry-masala-curry-seasoning"
          }
        },
        "071786a9-5547-4c5c-965d-66d2e670d34d": {
          "type": "text",
          "settings": {
            "popular_tag": "Amritsari Chole Masala",
            "link": "https:\/\/alcoeats.com\/products\/alco-cholle-masala-chickpea-seasoning"
          }
        },
        "393aec2c-224d-4198-a63b-0b88f32550c6": {
          "type": "text",
          "settings": {
            "popular_tag": "Meat Masala",
            "link": ""
          }
        },
        "b1042c0b-ff5e-497b-8591-792cf6244a7d": {
          "type": "text",
          "settings": {
            "popular_tag": "Pulao Masala",
            "link": ""
          }
        },
        "ff0f139a-bf4d-484d-baa1-ab5493c3386e": {
          "type": "text",
          "settings": {
            "popular_tag": "Magic Masala",
            "link": "https:\/\/alcoeats.com\/products\/alco-magic-masala"
          }
        },
        "8cf7021b-2b1c-40a9-9804-d33076d7fa4f": {
          "type": "text",
          "settings": {
            "popular_tag": "Meat Masala",
            "link": "https:\/\/alcoeats.com\/products\/alco-meat-masala"
          }
        },
        "f73abe18-38a9-4434-a6f7-438cc1a9bde8": {
          "type": "text",
          "settings": {
            "popular_tag": "Pulao Masala",
            "link": "https:\/\/alcoeats.com\/products\/pulao-masala"
          }
        },
        "f3ea21bf-f396-41f2-b332-2cac54436136": {
          "type": "text",
          "settings": {
            "popular_tag": "Magic Masala",
            "link": "https:\/\/alcoeats.com\/products\/alco-magic-masala"
          }
        },
        "a7aa0db2-2158-40b9-8f93-fa1aa34191e3": {
          "type": "text",
          "settings": {
            "popular_tag": "Vegetable Masala",
            "link": "https:\/\/alcoeats.com\/products\/alco-sabji-masala-vegetable-seasoning"
          }
        },
        "4de32744-226f-478d-a2f2-36a27f96a3e6": {
          "type": "text",
          "settings": {
            "popular_tag": "Sambar Masala",
            "link": "https:\/\/alcoeats.com\/products\/sambar-masala"
          }
        },
        "055d8072-7689-459b-9cbb-b1cb2b07ab56": {
          "type": "text",
          "settings": {
            "popular_tag": "Cashews",
            "link": "https:\/\/alcoeats.com\/collections\/cashews"
          }
        },
        "38a354da-b1b4-4a90-be41-bba8a2e75c16": {
          "type": "text",
          "settings": {
            "popular_tag": "Cashews in the Jar",
            "link": "https:\/\/alcoeats.com\/products\/cashews-in-the-jar"
          }
        },
        "0ab44634-d76e-4864-a36c-49314074ff5a": {
          "type": "text",
          "settings": {
            "popular_tag": "Peri-Peri Cashews",
            "link": "https:\/\/alcoeats.com\/products\/peri-peri-cashews-9oz"
          }
        },
        "2d81f820-1556-405c-aa24-4ab162735875": {
          "type": "text",
          "settings": {
            "popular_tag": "Mexican Taco Cashews",
            "link": "https:\/\/alcoeats.com\/products\/mexican-taco-cashews-9oz"
          }
        },
        "9505a681-21e2-48d8-81db-965e2114d367": {
          "type": "text",
          "settings": {
            "popular_tag": "Jalapeño &amp; Cheddar Cashews",
            "link": "https:\/\/alcoeats.com\/products\/jalapeno-cheddar-cashews-9oz"
          }
        },
        "bebfab91-bea9-490f-aa4b-865c4cae3284": {
          "type": "text",
          "settings": {
            "popular_tag": "Mi Amore Cashews",
            "link": "https:\/\/alcoeats.com\/products\/mi-amore-cashews"
          }
        },
        "673ab804-bebb-4b83-a109-676f97d9cd80": {
          "type": "text",
          "settings": {
            "popular_tag": "Cajun Kick Cashews",
            "link": "https:\/\/alcoeats.com\/products\/cajun-kick-cashews-9oz"
          }
        },
        "0655e20b-ff4a-41b2-b129-a81c805c86ae": {
          "type": "text",
          "settings": {
            "popular_tag": "Cashew Nut",
            "link": "https:\/\/alcoeats.com\/blogs\/alcoeats-101\/alcoeats-101-flavored-cashews"
          }
        },
        "e213d7d1-0040-46a1-9a64-197d47703710": {
          "type": "text",
          "settings": {
            "popular_tag": "Cashew Fruit",
            "link": "https:\/\/alcoeats.com\/collections\/sweet-cashews"
          }
        },
        "882f9d81-1b31-4976-b75f-89b3b4e83eae": {
          "type": "text",
          "settings": {
            "popular_tag": "Raw Cashews",
            "link": "https:\/\/alcoeats.com\/blogs\/grain-free\/are-cashews-nuts"
          }
        },
        "38159c4a-7701-41a3-bd6a-eb671aeff885": {
          "type": "text",
          "settings": {
            "popular_tag": "Honey Roasted Cashews",
            "link": "https:\/\/alcoeats.com\/blogs\/alcoeats-101\/types-of-cashews"
          }
        },
        "97e2c746-816a-435b-b42a-51ddbccb7a50": {
          "type": "text",
          "settings": {
            "popular_tag": "Roasted Cashews",
            "link": ""
          }
        },
        "28d165f3-9c6b-4b01-8d8b-ed8262ca3d29": {
          "type": "text",
          "settings": {
            "popular_tag": "Cashew Clusters",
            "link": "https:\/\/alcoeats.com\/products\/cashews-in-the-bag"
          }
        },
        "d0404a60-4b7c-4b9d-b6ba-cd6e1aed9c81": {
          "type": "text",
          "settings": {
            "popular_tag": "Cashew Peanuts",
            "link": "https:\/\/alcoeats.com\/products\/cashews-in-the-jar"
          }
        },
        "81987d9e-1144-4bd2-ac74-73948d4f18f6": {
          "type": "text",
          "settings": {
            "popular_tag": "Salted Cashews",
            "link": "https:\/\/alcoeats.com\/products\/simply-salted-cashews"
          }
        },
        "ac15f706-6ca3-4b7c-8ece-c989be409de9": {
          "type": "text",
          "settings": {
            "popular_tag": "Spicy Cashews",
            "link": "https:\/\/alcoeats.com\/products\/peri-peri-cashews-single-pack"
          }
        },
        "6e2d40d6-0f68-4be2-8e54-f8e0a307c142": {
          "type": "text",
          "settings": {
            "popular_tag": "Whole Cashews",
            "link": "https:\/\/alcoeats.com\/collections\/savory-cashews"
          }
        },
        "508c7ac0-64c7-4f0c-83fe-228a55e54ddd": {
          "type": "text",
          "settings": {
            "popular_tag": "Coffee Powder",
            "link": "https:\/\/alcoeats.com\/collections\/ground-coffee"
          }
        },
        "e9bf6cf9-4b42-41da-be4b-00d126c8d204": {
          "type": "text",
          "settings": {
            "popular_tag": "Maca Coffee",
            "link": "https:\/\/alcoeats.com\/blogs\/coffee\/chicory-coffee"
          }
        },
        "bc623e8f-dd63-4723-8d7d-c2f0a11749ba": {
          "type": "text",
          "settings": {
            "popular_tag": "",
            "link": ""
          }
        },
        "bd8fabc6-88a5-4c77-b016-cbfef2be045d": {
          "type": "text",
          "settings": {
            "popular_tag": "Espresso Powder",
            "link": "https:\/\/alcoeats.com\/products\/love-me-some-espresso-whole-beans-12oz"
          }
        },
        "efec192e-5386-401c-b8d9-38ea0452fe18": {
          "type": "text",
          "settings": {
            "popular_tag": "Coffee Grounds for Espresso",
            "link": "https:\/\/alcoeats.com\/products\/sip-snack-kit"
          }
        },
        "080edf6f-169f-458f-8ad5-70c032ee6d72": {
          "type": "text",
          "settings": {
            "popular_tag": "Instant Espresso Powder",
            "link": "https:\/\/alcoeats.com\/blogs\/recipes\/love-me-some-espresso"
          }
        },
        "6168d459-8f3c-42fa-b846-04c4c1b0b3fa": {
          "type": "text",
          "settings": {
            "popular_tag": "Matcha Coffee",
            "link": "https:\/\/alcoeats.com\/collections\/coffee"
          }
        },
        "5a443550-f317-4aa4-9212-9b257779dc5c": {
          "type": "text",
          "settings": {
            "popular_tag": "Black Powder Coffee",
            "link": "https:\/\/alcoeats.com\/blogs\/alcoeats-101\/coffee-benefits"
          }
        },
        "9cbe3092-c8da-4b51-8e2b-b750ef9f6394": {
          "type": "text",
          "settings": {
            "popular_tag": "Coffee Mate Powder",
            "link": "https:\/\/alcoeats.com\/collections\/coffee"
          }
        },
        "4e1e3cd1-8b4b-4d80-b630-0d6ebb4c02d9": {
          "type": "text",
          "settings": {
            "popular_tag": "Fine Ground Coffee",
            "link": "https:\/\/alcoeats.com\/collections\/ground-coffee"
          }
        },
        "f2034ec9-0b53-4562-a5b6-5a30c8efa62a": {
          "type": "text",
          "settings": {
            "popular_tag": "Cappuccino Powder",
            "link": "https:\/\/alcoeats.com\/products\/colombian-supremo-ground-12oz"
          }
        },
        "81301d2a-f225-4357-aa48-2e4ca99776f0": {
          "type": "text",
          "settings": {
            "popular_tag": "Hawaiian Blend - Ground",
            "link": ""
          }
        },
        "80d8dd32-cf56-4676-9d24-b0670b6e045b": {
          "type": "text",
          "settings": {
            "popular_tag": "Indonesian Sumatra",
            "link": "https:\/\/alcoeats.com\/products\/indonesian-sumatra-ground-8oz"
          }
        },
        "b27fbfca-2f14-4a78-9043-2a97fcdb3a8a": {
          "type": "text",
          "settings": {
            "popular_tag": "Bourbon Pecan - Ground",
            "link": "https:\/\/alcoeats.com\/products\/bourbon-pecan-ground-8oz"
          }
        },
        "7d9d7a95-ff47-454f-b792-89a11503679b": {
          "type": "text",
          "settings": {
            "popular_tag": "Appreciation Bundle",
            "link": "https:\/\/alcoeats.com\/products\/appreciation-bundle"
          }
        },
        "2f594f24-c1a4-4da3-ab8d-1144522bc85b": {
          "type": "text",
          "settings": {
            "popular_tag": "paneer masala",
            "link": "#"
          }
        }
      },
      "block_order": [
        "9b8d0c9d-9355-4ff8-95f6-b77fd85e02bf",
        "2a8652c7-ee84-457c-afd4-c944bd432081",
        "8ebccb83-b67f-4140-84fa-22524224f9b5",
        "494c2096-f838-4aeb-bbc2-8db24f537a88",
        "a3cff885-8b20-4cfd-9c4d-dd4318f10a1d",
        "8848b0b7-116d-4cc4-a56f-68557316b5f4",
        "ea6afd91-331d-461d-bbff-911547302bc7",
        "6e544a44-a8c9-45ed-a441-7e0ed28937f1",
        "071786a9-5547-4c5c-965d-66d2e670d34d",
        "393aec2c-224d-4198-a63b-0b88f32550c6",
        "b1042c0b-ff5e-497b-8591-792cf6244a7d",
        "ff0f139a-bf4d-484d-baa1-ab5493c3386e",
        "8cf7021b-2b1c-40a9-9804-d33076d7fa4f",
        "f73abe18-38a9-4434-a6f7-438cc1a9bde8",
        "f3ea21bf-f396-41f2-b332-2cac54436136",
        "a7aa0db2-2158-40b9-8f93-fa1aa34191e3",
        "4de32744-226f-478d-a2f2-36a27f96a3e6",
        "055d8072-7689-459b-9cbb-b1cb2b07ab56",
        "38a354da-b1b4-4a90-be41-bba8a2e75c16",
        "0ab44634-d76e-4864-a36c-49314074ff5a",
        "2d81f820-1556-405c-aa24-4ab162735875",
        "9505a681-21e2-48d8-81db-965e2114d367",
        "bebfab91-bea9-490f-aa4b-865c4cae3284",
        "673ab804-bebb-4b83-a109-676f97d9cd80",
        "0655e20b-ff4a-41b2-b129-a81c805c86ae",
        "e213d7d1-0040-46a1-9a64-197d47703710",
        "882f9d81-1b31-4976-b75f-89b3b4e83eae",
        "38159c4a-7701-41a3-bd6a-eb671aeff885",
        "97e2c746-816a-435b-b42a-51ddbccb7a50",
        "28d165f3-9c6b-4b01-8d8b-ed8262ca3d29",
        "d0404a60-4b7c-4b9d-b6ba-cd6e1aed9c81",
        "81987d9e-1144-4bd2-ac74-73948d4f18f6",
        "ac15f706-6ca3-4b7c-8ece-c989be409de9",
        "6e2d40d6-0f68-4be2-8e54-f8e0a307c142",
        "508c7ac0-64c7-4f0c-83fe-228a55e54ddd",
        "e9bf6cf9-4b42-41da-be4b-00d126c8d204",
        "bc623e8f-dd63-4723-8d7d-c2f0a11749ba",
        "bd8fabc6-88a5-4c77-b016-cbfef2be045d",
        "efec192e-5386-401c-b8d9-38ea0452fe18",
        "080edf6f-169f-458f-8ad5-70c032ee6d72",
        "6168d459-8f3c-42fa-b846-04c4c1b0b3fa",
        "5a443550-f317-4aa4-9212-9b257779dc5c",
        "9cbe3092-c8da-4b51-8e2b-b750ef9f6394",
        "4e1e3cd1-8b4b-4d80-b630-0d6ebb4c02d9",
        "f2034ec9-0b53-4562-a5b6-5a30c8efa62a",
        "81301d2a-f225-4357-aa48-2e4ca99776f0",
        "80d8dd32-cf56-4676-9d24-b0670b6e045b",
        "b27fbfca-2f14-4a78-9043-2a97fcdb3a8a",
        "7d9d7a95-ff47-454f-b792-89a11503679b",
        "2f594f24-c1a4-4da3-ab8d-1144522bc85b"
      ],
      "settings": {
        "heading": "popular tags"
      }
    }
  },
  "order": [
    "05e09d4d-92ad-4058-a1d7-2d438520a652",
    "0e5b9ff2-faef-4ccc-a78c-04c8577f97e7",
    "e3a122ce-a757-4467-943a-830f0eac79ba",
    "e623e5d7-4c52-4909-badc-b8e634abee1e",
    "25c87084-0b28-4d73-a6c6-6bea48b75abb",
    "406531c9-0259-4d83-9fda-8748d873d146",
    "7b5fab22-0054-4bd3-bc00-95b7a47aa786",
    "1d15a425-f7c8-4a8b-96a6-933b85893480",
    "06b56767-6a7e-41a1-a44b-eb8f447032fc",
    "d1fa8b77-b021-4105-819b-364db70036ec",
    "f3113dc4-eadf-4fa4-adf7-f288d07c1076"
  ]
}
